cmw/__init__.py
cmw/config.yaml
cmw/index.md
cmw/loader.py
cmw/template.html
cmw-11.0.16.dist-info/METADATA
cmw-11.0.16.dist-info/WHEEL
cmw-11.0.16.dist-info/entry_points.txt
cmw-11.0.16.dist-info/licenses/LICENSE
cmw-11.0.16.dist-info/RECORD
